backend/model/__init__.py
backend/model/config.py
langchain_models_config-0.0.1.dist-info/METADATA
langchain_models_config-0.0.1.dist-info/WHEEL
langchain_models_config-0.0.1.dist-info/top_level.txt
langchain_models_config-0.0.1.dist-info/RECORD
