Metadata-Version: 2.4
Name: langchain-models-config
Version: 0.0.1
Summary: A library for managing multiple LangChain model configurations with validation and automatic agent creation
Author-email: Andre Queiroz <andrequeiroz.com@gmail.com>
License: MIT
Project-URL: Homepage, https://github.com/andrequeiroz2/langchainAgent
Project-URL: Repository, https://github.com/andrequeiroz2/langchainAgent
Project-URL: Issues, https://github.com/andrequeiroz2/langchainAgent/issues
Keywords: langchain,llm,ai,configuration,agents,gemini,openai,anthropic
Classifier: Development Status :: 3 - Alpha
Classifier: Intended Audience :: Developers
Classifier: License :: OSI Approved :: MIT License
Classifier: Programming Language :: Python :: 3
Classifier: Programming Language :: Python :: 3.8
Classifier: Programming Language :: Python :: 3.9
Classifier: Programming Language :: Python :: 3.10
Classifier: Programming Language :: Python :: 3.11
Classifier: Programming Language :: Python :: 3.12
Classifier: Topic :: Software Development :: Libraries :: Python Modules
Classifier: Topic :: Scientific/Engineering :: Artificial Intelligence
Requires-Python: >=3.8
Requires-Dist: pydantic>=2.0.0
Requires-Dist: langchain-google-genai>=1.0.0
Requires-Dist: langchain-openai>=1.0.0
Requires-Dist: langchain-anthropic>=1.0.0
Provides-Extra: dev
Requires-Dist: pytest>=7.0.0; extra == "dev"
Requires-Dist: pytest-cov>=4.0.0; extra == "dev"
Requires-Dist: black>=23.0.0; extra == "dev"
Requires-Dist: ruff>=0.1.0; extra == "dev"
